docling_eval/__init__.py
docling_eval/py.typed
docling_eval/aggregations/consolidator.py
docling_eval/aggregations/multi_evalutor.py
docling_eval/campaign_tools/collect_images_from_cvat_xml.py
docling_eval/campaign_tools/combine_cvat_evaluations.py
docling_eval/campaign_tools/cvat_create_annotation_tasks_from_folders.py
docling_eval/campaign_tools/cvat_create_human_annotation_report.py
docling_eval/campaign_tools/cvat_evaluation_pipeline.py
docling_eval/campaign_tools/cvat_task_batch_uploader.py
docling_eval/campaign_tools/evaluate_cvat_tables.py
docling_eval/campaign_tools/merge_cvat_annotations.py
docling_eval/campaign_tools/run_cvat_deliveries_pipeline.py
docling_eval/cli/__init__.py
docling_eval/cli/cvat_to_docling_cli.py
docling_eval/cli/cvat_validator_cli.py
docling_eval/cli/main.py
docling_eval/cvat_tools/__init__.py
docling_eval/cvat_tools/analysis.py
docling_eval/cvat_tools/cvat_to_docling.py
docling_eval/cvat_tools/document.py
docling_eval/cvat_tools/folder_models.py
docling_eval/cvat_tools/folder_parser.py
docling_eval/cvat_tools/geometry.py
docling_eval/cvat_tools/models.py
docling_eval/cvat_tools/parser.py
docling_eval/cvat_tools/path_mappings.py
docling_eval/cvat_tools/tree.py
docling_eval/cvat_tools/utils.py
docling_eval/cvat_tools/validator.py
docling_eval/datamodels/__init__.py
docling_eval/datamodels/cvat_page_mapping.py
docling_eval/datamodels/cvat_types.py
docling_eval/datamodels/dataset_record.py
docling_eval/datamodels/types.py
docling_eval/dataset_builders/__init__.py
docling_eval/dataset_builders/cvat_dataset_builder.py
docling_eval/dataset_builders/cvat_preannotation_builder.py
docling_eval/dataset_builders/dataset_builder.py
docling_eval/dataset_builders/doclaynet_v1_builder.py
docling_eval/dataset_builders/doclaynet_v2_builder.py
docling_eval/dataset_builders/doclingdpbench_builder.py
docling_eval/dataset_builders/docvqa_builder.py
docling_eval/dataset_builders/dpbench_builder.py
docling_eval/dataset_builders/file_dataset_builder.py
docling_eval-0.10.0.dist-info/licenses/LICENSE
docling_eval-0.10.0.dist-info/METADATA
docling_eval-0.10.0.dist-info/WHEEL
docling_eval-0.10.0.dist-info/entry_points.txt
docling_eval-0.10.0.dist-info/top_level.txt
docling_eval-0.10.0.dist-info/RECORD
