Metadata-Version: 2.4
Name: docling-eval
Version: 0.10.0
Summary: Evaluation of Docling
Author-email: Peter Staar <taa@zurich.ibm.com>, Panos Vagenas <pva@zurich.ibm.com>, Ahmed Nassar <ahn@zurich.ibm.com>, Nikos Livathinos <nli@zurich.ibm.com>, Maxim Lysak <mly@zurich.ibm.com>, Michele Dolfi <dol@zurich.ibm.com>, Christoph Auer <cau@zurich.ibm.com>
License-Expression: MIT
Project-URL: homepage, https://github.com/docling-project/docling-eval
Project-URL: repository, https://github.com/docling-project/docling-eval
Project-URL: issues, https://github.com/docling-project/docling-eval/issues
Project-URL: changelog, https://github.com/docling-project/docling-eval/blob/main/CHANGELOG.md
Keywords: docling,evaluation,convert,document,pdf,docx,html,markdown,layout model,segmentation,table structure,table former
Classifier: Operating System :: MacOS :: MacOS X
Classifier: Operating System :: POSIX :: Linux
Classifier: Development Status :: 5 - Production/Stable
Classifier: Intended Audience :: Developers
Classifier: Intended Audience :: Science/Research
Classifier: Topic :: Scientific/Engineering :: Artificial Intelligence
Classifier: Programming Language :: Python :: 3
Requires-Python: <4.0,>=3.10
License-File: LICENSE
Requires-Dist: docling[vlm]<3.0.0,>=2.56.1
Requires-Dist: docling-core<3.0.0,>=2.48.0
Requires-Dist: pydantic<3.0.0,>=2.0.0
Requires-Dist: lxml<6.0.0,>=5.3.0
Requires-Dist: datasets<4.0.0,>=3.2.0
Requires-Dist: apted<2.0.0,>=1.0.3
Requires-Dist: Distance<0.2.0,>=0.1.3
Requires-Dist: matplotlib<4.0.0,>=3.10.0
Requires-Dist: torch<3.0.0,>=2.5.1
Requires-Dist: torchmetrics<2.0.0,>=1.6.0
Requires-Dist: pycocotools<3.0.0,>=2.0.8
Requires-Dist: tabulate<0.10.0,>=0.9.0
Requires-Dist: tqdm<5.0.0,>=4.67.1
Requires-Dist: pillow<12.0.0,>=10.3.0
Requires-Dist: evaluate<0.5.0,>=0.4.3
Requires-Dist: nltk<4.0.0,>=3.9.1
Requires-Dist: beautifulsoup4<5.0.0,>=4.12.3
Requires-Dist: jiwer<4.0.0,>=3.1.0
Requires-Dist: pandas<3.0.0,>=2.2.3
Requires-Dist: openpyxl<4.0.0,>=3.1.5
Requires-Dist: pypdf2<4.0.0,>=3.0.1
Requires-Dist: xmltodict<0.15.0,>=0.14.2
Requires-Dist: edit-distance<2.0.0,>=1.0.6
Requires-Dist: pyarrow>=20.0.0
Requires-Dist: typer>=0.16.0
Requires-Dist: scipy>=1.15.3
Requires-Dist: scipy-stubs>=1.15.3.0
Requires-Dist: editdistance>=0.8.1
Requires-Dist: reportlab>=4.4.3
Provides-Extra: hyperscalers
Requires-Dist: azure-ai-documentintelligence<2.0.0,>=1.0.2; extra == "hyperscalers"
Requires-Dist: azure-common<2.0.0,>=1.1.28; extra == "hyperscalers"
Requires-Dist: azure-core<2.0.0,>=1.33.0; extra == "hyperscalers"
Requires-Dist: boto3<2.0.0,>=1.37.8; extra == "hyperscalers"
Requires-Dist: google-cloud-documentai<4.0.0,>=3.2.0; extra == "hyperscalers"
Requires-Dist: ibm-cos-sdk<3.0.0,>=2.1.40; extra == "hyperscalers"
Provides-Extra: cvat-tools
Requires-Dist: cvat-sdk>=2.40.0; extra == "cvat-tools"
Requires-Dist: ocrmac>=1.0.0; (sys_platform == "darwin" and platform_machine == "arm64") and extra == "cvat-tools"
Dynamic: license-file
